{
  "apiVersion": "v0",
  "freshness": {
    "generatedAt": "2026-07-03T12:00:00Z",
    "snapshotDigest": "36f920af151bc66dfa0a93144857c004f08db1962d55991a70bfd0a1c44216b1",
    "staleAfter": "2026-07-04T12:00:00Z"
  },
  "identity": {
    "host": "github.com",
    "owner": "rust-lang",
    "repo": "rust",
    "source": "https://github.com/rust-lang/rust"
  },
  "selection": {
    "reason": "only_matching_record",
    "record": {
      "manifestPath": "repos/github.com/rust-lang/rust/record.toml",
      "record": {
        "mode": "overlay",
        "status": "verified",
        "source": "https://github.com/rust-lang/rust",
        "trust": {
          "confidence": "high",
          "provenance": [
            "imported",
            "verified"
          ],
          "notes": "Bootstrapped from `README.md` and `Cargo.toml`. Imported `repo.build` from `Cargo.toml`. Imported `repo.test` from `Cargo.toml`. This is an overlay bootstrap, not a maintainer-controlled canonical record. Auto-promoted to verified: all fields are honestly resolved."
        }
      },
      "artifacts": {
        "evidencePath": "repos/github.com/rust-lang/rust/evidence.md"
      }
    },
    "manifest": {
      "schema": "dotrepo/v0.1",
      "record": {
        "mode": "overlay",
        "status": "verified",
        "source": "https://github.com/rust-lang/rust",
        "generated_at": "2026-07-01T18:26:23.41634Z",
        "trust": {
          "confidence": "high",
          "provenance": [
            "imported",
            "verified"
          ],
          "notes": "Bootstrapped from `README.md` and `Cargo.toml`. Imported `repo.build` from `Cargo.toml`. Imported `repo.test` from `Cargo.toml`. This is an overlay bootstrap, not a maintainer-controlled canonical record. Auto-promoted to verified: all fields are honestly resolved."
        }
      },
      "repo": {
        "name": "rust",
        "description": "Read [\"Installation\"] from [The Book].",
        "homepage": "https://www.rust-lang.org",
        "license": "Apache-2.0",
        "status": null,
        "visibility": "public",
        "languages": [
          "Rust",
          "HTML",
          "Shell",
          "C",
          "JavaScript",
          "Python",
          "PowerShell",
          "TypeScript",
          "C++",
          "CSS",
          "Dockerfile",
          "Assembly",
          "Roff",
          "Linker Script",
          "Makefile",
          "Julia",
          "RenderScript",
          "Nix",
          "XSLT",
          "Emacs Lisp",
          "Batchfile",
          "RPC",
          "CMake",
          "LLVM",
          "Perl"
        ],
        "build": "cargo build --workspace",
        "test": "cargo test --workspace",
        "topics": [
          "rust",
          "compiler",
          "language"
        ]
      },
      "owners": null,
      "docs": {
        "root": "https://www.rust-lang.org",
        "getting_started": null,
        "architecture": null,
        "api": null
      },
      "readme": null,
      "compat": null,
      "relations": null,
      "x": {
        "github": {
          "archived": false,
          "clone_url": "https://github.com/rust-lang/rust.git",
          "default_branch": "main",
          "fork": false,
          "head_sha": "e2b71ade2db4ea263ab0d561d889f3e3795a500d",
          "html_url": "https://github.com/rust-lang/rust",
          "stars": 114184
        }
      }
    }
  },
  "conflicts": []
}