{
  "apiVersion": "v0",
  "freshness": {
    "generatedAt": "2026-06-29T06:00:00Z",
    "snapshotDigest": "2e779bd9bf404f50a1fbf44c58e6d1e86e42240d7360f2fac20a659d1f29e24e",
    "staleAfter": "2026-06-30T06:00:00Z"
  },
  "identity": {
    "host": "github.com",
    "owner": "gedoor",
    "repo": "legado",
    "source": "https://github.com/gedoor/legado"
  },
  "selection": {
    "reason": "only_matching_record",
    "record": {
      "manifestPath": "repos/github.com/gedoor/legado/record.toml",
      "record": {
        "mode": "overlay",
        "status": "verified",
        "source": "https://github.com/gedoor/legado",
        "trust": {
          "confidence": "high",
          "provenance": [
            "imported",
            "inferred",
            "verified"
          ],
          "notes": "Bootstrapped from `README.md`. Filled `repo.name` and `repo.description` with inferred defaults. This is an overlay bootstrap, not a maintainer-controlled canonical record. Auto-promoted to verified: all fields are honestly resolved."
        }
      },
      "artifacts": {
        "evidencePath": "repos/github.com/gedoor/legado/evidence.md"
      }
    },
    "manifest": {
      "schema": "dotrepo/v0.1",
      "record": {
        "mode": "overlay",
        "status": "verified",
        "source": "https://github.com/gedoor/legado",
        "generated_at": "2026-06-29T05:14:40.036738Z",
        "trust": {
          "confidence": "high",
          "provenance": [
            "imported",
            "inferred",
            "verified"
          ],
          "notes": "Bootstrapped from `README.md`. Filled `repo.name` and `repo.description` with inferred defaults. This is an overlay bootstrap, not a maintainer-controlled canonical record. Auto-promoted to verified: all fields are honestly resolved."
        }
      },
      "repo": {
        "name": "legado",
        "description": "Legado 3.0 Book Reader with powerful controls & full functions❤️阅读3.0, 阅读是一款可以自定义来源阅读网络内容的工具，为广大网络文学爱好者提供一种方便、快捷舒适的试读体验。",
        "homepage": "https://github.com/gedoor/legado",
        "license": null,
        "status": null,
        "visibility": "public",
        "languages": [
          "AMPL",
          "Batchfile",
          "CSS",
          "HTML",
          "Java",
          "JavaScript",
          "Kotlin",
          "Shell",
          "TypeScript",
          "Vue"
        ],
        "build": null,
        "test": null,
        "topics": []
      },
      "owners": null,
      "docs": null,
      "readme": null,
      "compat": null,
      "relations": null,
      "x": {
        "github": {
          "archived": false,
          "clone_url": "https://github.com/gedoor/legado.git",
          "default_branch": "main",
          "fork": false,
          "head_sha": "9bb0569269ed557753fc3866250970de6d454fcf",
          "html_url": "https://github.com/gedoor/legado",
          "stars": 46874
        }
      }
    }
  },
  "conflicts": []
}