{
  "apiVersion": "v0",
  "freshness": {
    "generatedAt": "2026-07-03T12:00:00Z",
    "snapshotDigest": "36f920af151bc66dfa0a93144857c004f08db1962d55991a70bfd0a1c44216b1",
    "staleAfter": "2026-07-04T12:00:00Z"
  },
  "identity": {
    "host": "github.com",
    "owner": "FormidableLabs",
    "repo": "prism-react-renderer",
    "source": "https://github.com/FormidableLabs/prism-react-renderer"
  },
  "selection": {
    "reason": "only_matching_record",
    "record": {
      "manifestPath": "repos/github.com/FormidableLabs/prism-react-renderer/record.toml",
      "record": {
        "mode": "overlay",
        "status": "verified",
        "source": "https://github.com/FormidableLabs/prism-react-renderer",
        "trust": {
          "confidence": "high",
          "provenance": [
            "imported",
            "verified"
          ],
          "notes": "Bootstrapped from `README.md` and `package.json`. Imported `repo.build` from `package.json`. Imported `repo.test` from `package.json`. This is an overlay bootstrap, not a maintainer-controlled canonical record. Auto-promoted to verified: all fields are honestly resolved."
        }
      },
      "artifacts": {
        "evidencePath": "repos/github.com/FormidableLabs/prism-react-renderer/evidence.md"
      }
    },
    "manifest": {
      "schema": "dotrepo/v0.1",
      "record": {
        "mode": "overlay",
        "status": "verified",
        "source": "https://github.com/FormidableLabs/prism-react-renderer",
        "generated_at": "2026-07-01T17:17:09.724317Z",
        "trust": {
          "confidence": "high",
          "provenance": [
            "imported",
            "verified"
          ],
          "notes": "Bootstrapped from `README.md` and `package.json`. Imported `repo.build` from `package.json`. Imported `repo.test` from `package.json`. This is an overlay bootstrap, not a maintainer-controlled canonical record. Auto-promoted to verified: all fields are honestly resolved."
        }
      },
      "repo": {
        "name": "Prism React Renderer",
        "description": "A lean Prism highlighter component for React",
        "homepage": "https://github.com/FormidableLabs/prism-react-renderer",
        "license": "MIT",
        "status": null,
        "visibility": "public",
        "languages": [
          "TypeScript",
          "CSS",
          "HTML"
        ],
        "build": "pnpm build",
        "test": "pnpm test",
        "topics": [
          "react",
          "reactjs",
          "prismjs",
          "highlight"
        ]
      },
      "owners": null,
      "docs": null,
      "readme": null,
      "compat": null,
      "relations": {
        "references": [],
        "links": [
          {
            "kind": "related",
            "target": "github.com/FormidableLabs/prism-react-renderer",
            "notes": "Declared repository in package.json.",
            "trust": {
              "confidence": "low",
              "provenance": [
                "declared",
                "manifest"
              ],
              "notes": null
            }
          }
        ]
      },
      "x": {
        "github": {
          "archived": false,
          "clone_url": "https://github.com/FormidableLabs/prism-react-renderer.git",
          "default_branch": "master",
          "fork": false,
          "head_sha": "e1c83a468b05df7f452b3ad7e4ae5ab874574d4e",
          "html_url": "https://github.com/FormidableLabs/prism-react-renderer",
          "stars": 1994
        }
      }
    }
  },
  "conflicts": []
}