{
  "apiVersion": "v0",
  "freshness": {
    "generatedAt": "2026-06-29T06:00:00Z",
    "snapshotDigest": "2e779bd9bf404f50a1fbf44c58e6d1e86e42240d7360f2fac20a659d1f29e24e",
    "staleAfter": "2026-06-30T06:00:00Z"
  },
  "identity": {
    "host": "github.com",
    "owner": "gradio-app",
    "repo": "gradio",
    "source": "https://github.com/gradio-app/gradio"
  },
  "repository": {
    "name": "gradio",
    "description": "Build and share delightful machine learning apps, all in Python. 🌟 Star to support our work!",
    "homepage": "http://www.gradio.app",
    "docsRoot": "https://gradio.app/docs/",
    "gettingStarted": "https://gradio.app/getting_started/",
    "securityContact": "gradio-team@huggingface.co"
  },
  "selection": {
    "reason": "only_matching_record",
    "record": {
      "manifestPath": "repos/github.com/gradio-app/gradio/record.toml",
      "record": {
        "mode": "overlay",
        "status": "verified",
        "source": "https://github.com/gradio-app/gradio",
        "trust": {
          "confidence": "high",
          "provenance": [
            "imported",
            "inferred",
            "verified"
          ],
          "notes": "Bootstrapped from `README.md`, `SECURITY.md`, and `pyproject.toml`. Filled `repo.description` with inferred defaults. Imported `repo.build` from `pyproject.toml`. Imported `repo.test` from `pyproject.toml`. This is an overlay bootstrap, not a maintainer-controlled canonical record. Auto-promoted to verified: all fields are honestly resolved."
        }
      },
      "artifacts": {
        "evidencePath": "repos/github.com/gradio-app/gradio/evidence.md"
      }
    }
  },
  "conflicts": [],
  "links": {
    "self": "/v0/repos/github.com/gradio-app/gradio/index.json",
    "trust": "/v0/repos/github.com/gradio-app/gradio/trust.json",
    "profile": "/v0/repos/github.com/gradio-app/gradio/profile.json",
    "queryTemplate": "/v0/repos/github.com/gradio-app/gradio/query?path={dot_path}",
    "indexPath": "repos/github.com/gradio-app/gradio/"
  }
}