{
  "apiVersion": "v0",
  "freshness": {
    "generatedAt": "2026-06-29T02:21:50Z",
    "snapshotDigest": "ed1bc67945214676a7189b186f684dc8e1e54ad1e0544cb52de86c79dac42cfc",
    "staleAfter": "2026-07-06T02:21:50Z"
  },
  "identity": {
    "host": "github.com",
    "owner": "actix",
    "repo": "actix-web",
    "source": "https://github.com/actix/actix-web"
  },
  "repository": {
    "name": "actix-web",
    "description": "Actix Web is a powerful, pragmatic, and extremely fast web framework for Rust.",
    "homepage": "https://actix.rs",
    "docsRoot": "https://actix.rs"
  },
  "selection": {
    "reason": "only_matching_record",
    "record": {
      "manifestPath": "repos/github.com/actix/actix-web/record.toml",
      "record": {
        "mode": "overlay",
        "status": "verified",
        "source": "https://github.com/actix/actix-web",
        "trust": {
          "confidence": "high",
          "provenance": [
            "imported",
            "inferred",
            "verified"
          ],
          "notes": "Bootstrapped from `Cargo.toml`. Filled `repo.name` and `repo.description` with inferred defaults. Imported `repo.build` from `Cargo.toml`. Imported `repo.test` from `Cargo.toml`. This is an overlay bootstrap, not a maintainer-controlled canonical record. Auto-promoted to verified: all fields are honestly resolved."
        }
      },
      "artifacts": {
        "evidencePath": "repos/github.com/actix/actix-web/evidence.md"
      }
    }
  },
  "conflicts": [],
  "links": {
    "self": "/v0/repos/github.com/actix/actix-web/index.json",
    "trust": "/v0/repos/github.com/actix/actix-web/trust.json",
    "profile": "/v0/repos/github.com/actix/actix-web/profile.json",
    "queryTemplate": "/v0/repos/github.com/actix/actix-web/query?path={dot_path}",
    "indexPath": "repos/github.com/actix/actix-web/"
  }
}