{
  "apiVersion": "v0",
  "freshness": {
    "generatedAt": "2026-07-03T12:00:00Z",
    "snapshotDigest": "36f920af151bc66dfa0a93144857c004f08db1962d55991a70bfd0a1c44216b1",
    "staleAfter": "2026-07-04T12:00:00Z"
  },
  "identity": {
    "host": "github.com",
    "owner": "diggerhq",
    "repo": "digger",
    "source": "https://github.com/diggerhq/digger"
  },
  "repository": {
    "name": "digger",
    "description": "Heads-up: We’ve rebranded! Starting from 7th November 2025, the Digger project is now OpenTaco.",
    "homepage": "https://digger.dev",
    "docsRoot": "https://docs.digger.dev/",
    "gettingStarted": "https://docs.digger.dev/getting-started/github-actions-+-aws"
  },
  "selection": {
    "reason": "only_matching_record",
    "record": {
      "manifestPath": "repos/github.com/diggerhq/digger/record.toml",
      "record": {
        "mode": "overlay",
        "status": "verified",
        "source": "https://github.com/diggerhq/digger",
        "trust": {
          "confidence": "high",
          "provenance": [
            "imported",
            "verified"
          ],
          "notes": "Bootstrapped from `README.md` and `go.mod`. Imported `repo.build` from `go.mod`. Imported `repo.test` from `go.mod`. This is an overlay bootstrap, not a maintainer-controlled canonical record. Auto-promoted to verified: all fields are honestly resolved."
        }
      },
      "artifacts": {
        "evidencePath": "repos/github.com/diggerhq/digger/evidence.md"
      }
    }
  },
  "conflicts": [],
  "links": {
    "self": "/v0/repos/github.com/diggerhq/digger/index.json",
    "trust": "/v0/repos/github.com/diggerhq/digger/trust.json",
    "profile": "/v0/repos/github.com/diggerhq/digger/profile.json",
    "queryTemplate": "/v0/repos/github.com/diggerhq/digger/query?path={dot_path}",
    "indexPath": "repos/github.com/diggerhq/digger/"
  }
}