{
  "apiVersion": "v0",
  "freshness": {
    "generatedAt": "2026-03-10T18:30:00Z",
    "snapshotDigest": "a0d8dddce221cf8445cd14754caa02d4d96e23f8322c66026f70880a9a9dedaa",
    "staleAfter": "2026-03-11T18:30:00Z"
  },
  "identity": {
    "host": "github.com",
    "owner": "BurntSushi",
    "repo": "ripgrep",
    "source": "https://github.com/BurntSushi/ripgrep"
  },
  "repository": {
    "name": "ripgrep",
    "description": "Line-oriented search tool that recursively searches the current directory for a regex pattern.",
    "homepage": "https://github.com/BurntSushi/ripgrep",
    "docsRoot": "docs/"
  },
  "selection": {
    "reason": "only_matching_record",
    "record": {
      "manifestPath": "repos/github.com/BurntSushi/ripgrep/record.toml",
      "record": {
        "mode": "overlay",
        "status": "imported",
        "source": "https://github.com/BurntSushi/ripgrep",
        "trust": {
          "confidence": "medium",
          "provenance": [
            "imported",
            "inferred"
          ],
          "notes": "Imported from public repository materials; build and test commands are inferred from the Cargo project layout; not maintainer-verified."
        }
      },
      "artifacts": {
        "evidencePath": "repos/github.com/BurntSushi/ripgrep/evidence.md"
      }
    }
  },
  "conflicts": [],
  "links": {
    "self": "/v0/repos/github.com/BurntSushi/ripgrep/index.json",
    "trust": "/v0/repos/github.com/BurntSushi/ripgrep/trust.json",
    "queryTemplate": "/v0/repos/github.com/BurntSushi/ripgrep/query?path={dot_path}",
    "indexPath": "repos/github.com/BurntSushi/ripgrep/"
  }
}