{
  "apiVersion": "v0",
  "freshness": {
    "generatedAt": "2026-07-03T12:00:00Z",
    "snapshotDigest": "36f920af151bc66dfa0a93144857c004f08db1962d55991a70bfd0a1c44216b1",
    "staleAfter": "2026-07-04T12:00:00Z"
  },
  "identity": {
    "host": "github.com",
    "owner": "jgm",
    "repo": "pandoc",
    "source": "https://github.com/jgm/pandoc"
  },
  "record": {
    "manifestPath": "repos/github.com/jgm/pandoc/record.toml",
    "mode": "overlay",
    "source": "https://github.com/jgm/pandoc",
    "generatedAt": "2026-07-01T18:09:51.462712Z",
    "evidencePath": "repos/github.com/jgm/pandoc/evidence.md"
  },
  "purpose": "Pandoc is a Haskell library for converting from one markup format to another, and a command-line tool that uses this library.",
  "name": "Pandoc",
  "homepage": "https://pandoc.org",
  "license": "GPL-2.0",
  "visibility": "public",
  "languages": [
    "Haskell",
    "Roff",
    "Rich Text Format",
    "HTML",
    "Lua",
    "JavaScript",
    "Jupyter Notebook",
    "Typst",
    "Makefile",
    "Python",
    "Shell",
    "TeX",
    "Nix",
    "CSS",
    "Perl",
    "Smarty",
    "Emacs Lisp",
    "Ruby"
  ],
  "topics": [
    "pandoc",
    "haskell",
    "markdown",
    "markup",
    "converter",
    "publishing",
    "document",
    "presentation",
    "commonmark"
  ],
  "execution": {
    "build": "make build",
    "test": "make test"
  },
  "docs": {
    "root": "https://pandoc.org"
  },
  "ownership": {
    "securityContact": "jgm@berkeley.edu"
  },
  "completeness": {
    "hasBuild": true,
    "hasTest": true,
    "hasDocs": true,
    "hasSecurityContact": true,
    "hasOwnershipSignal": false,
    "hasLicense": true,
    "conflictCount": 0
  },
  "trust": {
    "selectedStatus": "verified",
    "confidence": "high",
    "provenance": [
      "imported",
      "verified"
    ],
    "selectionReason": "only_matching_record"
  },
  "conflicts": [],
  "links": {
    "self": "/v0/repos/github.com/jgm/pandoc/profile.json",
    "repository": "/v0/repos/github.com/jgm/pandoc/index.json",
    "trust": "/v0/repos/github.com/jgm/pandoc/trust.json",
    "queryTemplate": "/v0/repos/github.com/jgm/pandoc/query?path={dot_path}",
    "indexPath": "repos/github.com/jgm/pandoc/"
  }
}