{
  "apiVersion": "v0",
  "freshness": {
    "generatedAt": "2026-07-03T12:00:00Z",
    "snapshotDigest": "36f920af151bc66dfa0a93144857c004f08db1962d55991a70bfd0a1c44216b1",
    "staleAfter": "2026-07-04T12:00:00Z"
  },
  "identity": {
    "host": "github.com",
    "owner": "recloudstream",
    "repo": "cloudstream",
    "source": "https://github.com/recloudstream/cloudstream"
  },
  "record": {
    "manifestPath": "repos/github.com/recloudstream/cloudstream/record.toml",
    "mode": "overlay",
    "source": "https://github.com/recloudstream/cloudstream",
    "generatedAt": "2026-07-01T18:24:41.960814Z",
    "evidencePath": "repos/github.com/recloudstream/cloudstream/evidence.md"
  },
  "purpose": "⚠️ Warning: By default, this app doesn't provide any video sources; you have to install extensions to add functionality to the app.",
  "name": "CloudStream",
  "homepage": "https://github.com/recloudstream/cloudstream",
  "license": "GPL-3.0",
  "visibility": "public",
  "languages": [
    "Kotlin"
  ],
  "topics": [
    "android",
    "video-streaming",
    "media-center",
    "home-theater",
    "multimedia",
    "good-first-issue"
  ],
  "execution": {
    "build": "./gradlew build",
    "test": "./gradlew test"
  },
  "docs": {
    "gettingStarted": "https://recloudstream.github.io/csdocs/"
  },
  "ownership": {},
  "completeness": {
    "hasBuild": true,
    "hasTest": true,
    "hasDocs": true,
    "hasSecurityContact": false,
    "hasOwnershipSignal": false,
    "hasLicense": true,
    "conflictCount": 0
  },
  "trust": {
    "selectedStatus": "verified",
    "confidence": "high",
    "provenance": [
      "imported",
      "verified"
    ],
    "selectionReason": "only_matching_record"
  },
  "conflicts": [],
  "links": {
    "self": "/v0/repos/github.com/recloudstream/cloudstream/profile.json",
    "repository": "/v0/repos/github.com/recloudstream/cloudstream/index.json",
    "trust": "/v0/repos/github.com/recloudstream/cloudstream/trust.json",
    "queryTemplate": "/v0/repos/github.com/recloudstream/cloudstream/query?path={dot_path}",
    "indexPath": "repos/github.com/recloudstream/cloudstream/"
  }
}