{
  "apiVersion": "v0",
  "freshness": {
    "generatedAt": "2026-07-03T12:00:00Z",
    "snapshotDigest": "36f920af151bc66dfa0a93144857c004f08db1962d55991a70bfd0a1c44216b1",
    "staleAfter": "2026-07-04T12:00:00Z"
  },
  "identity": {
    "host": "github.com",
    "owner": "Avaiga",
    "repo": "taipy",
    "source": "https://github.com/Avaiga/taipy"
  },
  "selection": {
    "reason": "only_matching_record",
    "record": {
      "manifestPath": "repos/github.com/Avaiga/taipy/record.toml",
      "record": {
        "mode": "overlay",
        "status": "verified",
        "source": "https://github.com/Avaiga/taipy",
        "trust": {
          "confidence": "high",
          "provenance": [
            "imported",
            "verified"
          ],
          "notes": "Bootstrapped from `README.md`, `SECURITY.md`, and `pyproject.toml`. SECURITY.md provided a policy or reporting URL rather than a direct mailbox, so `security_contact` preserves that URL. Imported `repo.build` from `pyproject.toml`. Imported `repo.test` from `pyproject.toml`. This is an overlay bootstrap, not a maintainer-controlled canonical record. Auto-promoted to verified: all fields are honestly resolved."
        }
      },
      "artifacts": {
        "evidencePath": "repos/github.com/Avaiga/taipy/evidence.md"
      }
    },
    "manifest": {
      "schema": "dotrepo/v0.1",
      "record": {
        "mode": "overlay",
        "status": "verified",
        "source": "https://github.com/Avaiga/taipy",
        "generated_at": "2026-07-01T17:15:35.470316Z",
        "trust": {
          "confidence": "high",
          "provenance": [
            "imported",
            "verified"
          ],
          "notes": "Bootstrapped from `README.md`, `SECURITY.md`, and `pyproject.toml`. SECURITY.md provided a policy or reporting URL rather than a direct mailbox, so `security_contact` preserves that URL. Imported `repo.build` from `pyproject.toml`. Imported `repo.test` from `pyproject.toml`. This is an overlay bootstrap, not a maintainer-controlled canonical record. Auto-promoted to verified: all fields are honestly resolved."
        }
      },
      "repo": {
        "name": "Taipy",
        "description": "Build Python Data & AI web applications",
        "homepage": "https://www.taipy.io",
        "license": "Apache-2.0",
        "status": null,
        "visibility": "public",
        "languages": [
          "Python",
          "TypeScript",
          "CSS",
          "JavaScript",
          "Jupyter Notebook",
          "Jinja",
          "HTML",
          "Shell",
          "Dockerfile"
        ],
        "build": "python -m build",
        "test": "python -m pytest",
        "topics": [
          "automation",
          "data-engineering",
          "data-ops",
          "data-visualization",
          "datascience",
          "developer-tools",
          "mlops",
          "orchestration",
          "pipeline",
          "pipelines",
          "python",
          "taipy-gui",
          "workflow",
          "taipy-core",
          "hacktoberfest",
          "hacktoberfest2023",
          "data-integration",
          "job-scheduler",
          "scenario",
          "scenario-analysis"
        ]
      },
      "owners": {
        "maintainers": [],
        "team": null,
        "security_contact": "https://github.com/Avaiga/taipy/security"
      },
      "docs": {
        "root": "https://docs.taipy.io/en/latest/refmans/",
        "getting_started": "https://cdn.sanity.io/images/12yo38rb/production/f1ffeaabe94c5605d20321f0f417fef69b8d48f8-1860x600.png",
        "architecture": null,
        "api": null
      },
      "readme": null,
      "compat": null,
      "relations": null,
      "x": {
        "github": {
          "archived": false,
          "clone_url": "https://github.com/Avaiga/taipy.git",
          "default_branch": "develop",
          "fork": false,
          "head_sha": "5bcb5749521f9ddcc725c009aca00a88ff724e87",
          "html_url": "https://github.com/Avaiga/taipy",
          "stars": 19254
        }
      }
    }
  },
  "conflicts": []
}