{
  "apiVersion": "v0",
  "freshness": {
    "generatedAt": "2026-03-10T18:30:00Z",
    "snapshotDigest": "a0d8dddce221cf8445cd14754caa02d4d96e23f8322c66026f70880a9a9dedaa",
    "staleAfter": "2026-03-11T18:30:00Z"
  },
  "repositoryCount": 10,
  "repositories": [
    {
      "identity": {
        "host": "github.com",
        "owner": "BurntSushi",
        "repo": "ripgrep",
        "source": "https://github.com/BurntSushi/ripgrep"
      },
      "name": "ripgrep",
      "description": "Line-oriented search tool that recursively searches the current directory for a regex pattern.",
      "links": {
        "self": "/v0/repos/github.com/BurntSushi/ripgrep/index.json",
        "trust": "/v0/repos/github.com/BurntSushi/ripgrep/trust.json",
        "queryTemplate": "/v0/repos/github.com/BurntSushi/ripgrep/query?path={dot_path}",
        "indexPath": "repos/github.com/BurntSushi/ripgrep/"
      }
    },
    {
      "identity": {
        "host": "github.com",
        "owner": "caddyserver",
        "repo": "caddy",
        "source": "https://github.com/caddyserver/caddy"
      },
      "name": "Caddy",
      "description": "Fast and extensible multi-platform HTTP/1-2-3 web server with automatic HTTPS",
      "links": {
        "self": "/v0/repos/github.com/caddyserver/caddy/index.json",
        "trust": "/v0/repos/github.com/caddyserver/caddy/trust.json",
        "queryTemplate": "/v0/repos/github.com/caddyserver/caddy/query?path={dot_path}",
        "indexPath": "repos/github.com/caddyserver/caddy/"
      }
    },
    {
      "identity": {
        "host": "github.com",
        "owner": "cli",
        "repo": "cli",
        "source": "https://github.com/cli/cli"
      },
      "name": "GitHub CLI",
      "description": "GitHub's official command line tool",
      "links": {
        "self": "/v0/repos/github.com/cli/cli/index.json",
        "trust": "/v0/repos/github.com/cli/cli/trust.json",
        "queryTemplate": "/v0/repos/github.com/cli/cli/query?path={dot_path}",
        "indexPath": "repos/github.com/cli/cli/"
      }
    },
    {
      "identity": {
        "host": "github.com",
        "owner": "fastapi",
        "repo": "fastapi",
        "source": "https://github.com/fastapi/fastapi"
      },
      "name": "FastAPI",
      "description": "FastAPI framework, high performance, easy to learn, fast to code, ready for production",
      "links": {
        "self": "/v0/repos/github.com/fastapi/fastapi/index.json",
        "trust": "/v0/repos/github.com/fastapi/fastapi/trust.json",
        "queryTemplate": "/v0/repos/github.com/fastapi/fastapi/query?path={dot_path}",
        "indexPath": "repos/github.com/fastapi/fastapi/"
      }
    },
    {
      "identity": {
        "host": "github.com",
        "owner": "maxwellsantoro",
        "repo": "ries-rs",
        "source": "https://github.com/maxwellsantoro/ries-rs"
      },
      "name": "RIES-RS",
      "description": "High-performance Rust reimplementation of Robert Munafo's RIES (RILYBOT Inverse Equation Solver). Given any target number, it discovers elegant algebraic expressions and equations that evaluate exactly to it - now with parallel search, PSLQ integer relations, Python bindings, and WebAssembly support.",
      "links": {
        "self": "/v0/repos/github.com/maxwellsantoro/ries-rs/index.json",
        "trust": "/v0/repos/github.com/maxwellsantoro/ries-rs/trust.json",
        "queryTemplate": "/v0/repos/github.com/maxwellsantoro/ries-rs/query?path={dot_path}",
        "indexPath": "repos/github.com/maxwellsantoro/ries-rs/"
      }
    },
    {
      "identity": {
        "host": "github.com",
        "owner": "serde-rs",
        "repo": "serde",
        "source": "https://github.com/serde-rs/serde"
      },
      "name": "Serde",
      "description": "Serde is a framework for *ser*ializing and *de*serializing Rust data structures efficiently and generically.",
      "links": {
        "self": "/v0/repos/github.com/serde-rs/serde/index.json",
        "trust": "/v0/repos/github.com/serde-rs/serde/trust.json",
        "queryTemplate": "/v0/repos/github.com/serde-rs/serde/query?path={dot_path}",
        "indexPath": "repos/github.com/serde-rs/serde/"
      }
    },
    {
      "identity": {
        "host": "github.com",
        "owner": "sharkdp",
        "repo": "bat",
        "source": "https://github.com/sharkdp/bat"
      },
      "name": "bat",
      "description": "A cat(1) clone with syntax highlighting and Git integration.",
      "links": {
        "self": "/v0/repos/github.com/sharkdp/bat/index.json",
        "trust": "/v0/repos/github.com/sharkdp/bat/trust.json",
        "queryTemplate": "/v0/repos/github.com/sharkdp/bat/query?path={dot_path}",
        "indexPath": "repos/github.com/sharkdp/bat/"
      }
    },
    {
      "identity": {
        "host": "github.com",
        "owner": "sharkdp",
        "repo": "fd",
        "source": "https://github.com/sharkdp/fd"
      },
      "name": "fd",
      "description": "A simple, fast and user-friendly alternative to 'find'.",
      "links": {
        "self": "/v0/repos/github.com/sharkdp/fd/index.json",
        "trust": "/v0/repos/github.com/sharkdp/fd/trust.json",
        "queryTemplate": "/v0/repos/github.com/sharkdp/fd/query?path={dot_path}",
        "indexPath": "repos/github.com/sharkdp/fd/"
      }
    },
    {
      "identity": {
        "host": "github.com",
        "owner": "tokio-rs",
        "repo": "tokio",
        "source": "https://github.com/tokio-rs/tokio"
      },
      "name": "Tokio",
      "description": "A runtime for writing reliable, asynchronous, and slim applications with the Rust programming language.",
      "links": {
        "self": "/v0/repos/github.com/tokio-rs/tokio/index.json",
        "trust": "/v0/repos/github.com/tokio-rs/tokio/trust.json",
        "queryTemplate": "/v0/repos/github.com/tokio-rs/tokio/query?path={dot_path}",
        "indexPath": "repos/github.com/tokio-rs/tokio/"
      }
    },
    {
      "identity": {
        "host": "github.com",
        "owner": "vitejs",
        "repo": "vite",
        "source": "https://github.com/vitejs/vite"
      },
      "name": "Vite",
      "description": "Next generation frontend tooling. It's fast!",
      "links": {
        "self": "/v0/repos/github.com/vitejs/vite/index.json",
        "trust": "/v0/repos/github.com/vitejs/vite/trust.json",
        "queryTemplate": "/v0/repos/github.com/vitejs/vite/query?path={dot_path}",
        "indexPath": "repos/github.com/vitejs/vite/"
      }
    }
  ]
}